AUTHORS
CHANGELOG.txt
DESCRIPTION
LICENSE
MANIFEST.in
README.rst
setup.py
crowdsourced_fields/__init__.py
crowdsourced_fields/admin.py
crowdsourced_fields/forms.py
crowdsourced_fields/models.py
crowdsourced_fields/migrations/0001_initial.py
crowdsourced_fields/migrations/0002_auto__add_field_crowdsourceditemgenericforeignkey_field_name__del_uniq.py
crowdsourced_fields/migrations/__init__.py
crowdsourced_fields/static/crowdsourced_fields/css/combobox.css
crowdsourced_fields/static/crowdsourced_fields/js/combobox.js
crowdsourced_fields/tests/__init__.py
crowdsourced_fields/tests/admin_tests.py
crowdsourced_fields/tests/factories.py
crowdsourced_fields/tests/forms_tests.py
crowdsourced_fields/tests/models_tests.py
crowdsourced_fields/tests/runtests.py
crowdsourced_fields/tests/south_settings.py
crowdsourced_fields/tests/test_settings.py
crowdsourced_fields/tests/urls.py
crowdsourced_fields/tests/test_app/__init__.py
crowdsourced_fields/tests/test_app/forms.py
crowdsourced_fields/tests/test_app/models.py
crowdsourced_fields/tests/test_app/urls.py
crowdsourced_fields/tests/test_app/views.py
crowdsourced_fields/tests/test_app/templates/500.html
crowdsourced_fields/tests/test_app/templates/test_app/test_view.html
crowdsourced_fields/tests/test_static/js/jquery-1.7.0.min.js
crowdsourced_fields/tests/test_static/js/jquery-ui-1.8.16.custom.min.js
django_crowdsourced_fields.egg-info/PKG-INFO
django_crowdsourced_fields.egg-info/SOURCES.txt
django_crowdsourced_fields.egg-info/dependency_links.txt
django_crowdsourced_fields.egg-info/top_level.txt