Metadata-Version: 1.0
Name: django-crowdsourced-fields
Version: 0.4
Summary: A reusable Django app that allows to mark certain fields of your models as
